ddna.py
helpers/__init__.py
helpers/utils.py
test/__init__.py
test/test_ddna.py
ddna-0.1.2.dist-info/LICENSE
ddna-0.1.2.dist-info/METADATA
ddna-0.1.2.dist-info/WHEEL
ddna-0.1.2.dist-info/top_level.txt
ddna-0.1.2.dist-info/RECORD
