Metadata-Version: 2.1
Name: ddna
Version: 0.1.2
Summary: Encode and decode strings to DNA
Home-page: https://github.com/Aayush9029/DDNA
Author: Aayush Pokharel
Author-email: aayushpokharel36@gmail.com
License: UNKNOWN
Platform: UNKNOWN
Classifier: Programming Language :: Python
Classifier: Programming Language :: Python :: 3
Classifier: Programming Language :: Python :: 3.6
Classifier: Programming Language :: Python :: 3.7
Classifier: Programming Language :: Python :: 3.8
Classifier: License :: OSI Approved :: MIT License
Classifier: Operating System :: OS Independent
License-File: LICENSE
